{
    "DNDConfig": null,
    "_height_": {
        "type": "string",
        "value": "42%"
    },
    "_left_": {
        "type": "string",
        "value": "0"
    },
    "_margin_": [
        0,
        0,
        0,
        0
    ],
    "_orientation_": 6,
    "_padding_": [
        0,
        0,
        0,
        0
    ],
    "_percent_": true,
    "_skin_": "s52efebb1e6941fdaf52560354be1a4e",
    "_top_": {
        "type": "string",
        "value": "1%"
    },
    "_width_": {
        "type": "string",
        "value": "100%"
    },
    "allboxes": [],
    "autogrowmode": 0,
    "canUpdateUI": true,
    "children": [
        "flxItem1",
        "flxItem2",
        "flxItem3",
        "flxItem4",
        "flxItem5",
        "flxItem6",
        "flxItem7",
        "flxItem8"
    ],
    "clipbounds": true,
    "containerweight": 100,
    "enablescrolling": true,
    "id": "flxCalendarShow",
    "info": null,
    "iscustomlayout": false,
    "isvisible": true,
    "kuid": "c0f45ff63cb548f39f2f321ee91a2142",
    "layouttype": 3,
    "name": "kony.ui.FlexContainer",
    "parent": "flxAuctionCalendarDetails",
    "pf": "frmAuctionCalendar",
    "retaincontentalignment": false,
    "retainflexpositionproperties": false,
    "retainflowhorizontalalignment": false,
    "snapgridsize": 10,
    "snaptogrid": true,
    "wType": "FlexContainer",
    "widgetalignment": 1
}