{
    "@class": "com.kony.gen.viz.model.container.KVizSegment2",
    "DNDConfig": null,
    "_data_": [
        {
            "btnDone": {
                "@class": "com.viz.ide.model.segment.SimpleTextSegmentData",
                "text": "Done"
            },
            "lblAddRequest": {
                "@class": "com.viz.ide.model.segment.SimpleTextSegmentData",
                "text": "Label"
            },
            "lblAddRequestValue": {
                "@class": "com.viz.ide.model.segment.SimpleTextSegmentData",
                "text": "Label"
            },
            "lblAdded": {
                "@class": "com.viz.ide.model.segment.SimpleTextSegmentData",
                "text": "Label"
            },
            "lblAddedValue": {
                "@class": "com.viz.ide.model.segment.SimpleTextSegmentData",
                "text": "Label"
            },
            "lblAuctionId": {
                "@class": "com.viz.ide.model.segment.SimpleTextSegmentData",
                "text": "Label"
            },
            "lblAuctionIdValue": {
                "@class": "com.viz.ide.model.segment.SimpleTextSegmentData",
                "text": "Label"
            },
            "lblChassisNo": {
                "@class": "com.viz.ide.model.segment.SimpleTextSegmentData",
                "text": "Label"
            },
            "lblChassisNoValue": {
                "@class": "com.viz.ide.model.segment.SimpleTextSegmentData",
                "text": "Label"
            },
            "lblDone": {
                "@class": "com.viz.ide.model.segment.SimpleTextSegmentData",
                "text": "Label"
            },
            "lblLocation": {
                "@class": "com.viz.ide.model.segment.SimpleTextSegmentData",
                "text": "Label"
            },
            "lblLocationValue": {
                "@class": "com.viz.ide.model.segment.SimpleTextSegmentData",
                "text": "Label"
            },
            "lblModel": {
                "@class": "com.viz.ide.model.segment.SimpleTextSegmentData",
                "text": "Label"
            },
            "lblModelValue": {
                "@class": "com.viz.ide.model.segment.SimpleTextSegmentData",
                "text": "Label"
            },
            "lblTargetSellingPrice": {
                "@class": "com.viz.ide.model.segment.SimpleTextSegmentData",
                "text": "Label"
            },
            "lblUploadFile": {
                "@class": "com.viz.ide.model.segment.SimpleTextSegmentData",
                "text": "Label"
            },
            "lblUploadFileValue": {
                "@class": "com.viz.ide.model.segment.SimpleTextSegmentData",
                "text": "Label"
            },
            "lbltargetSellingPriceValue": {
                "@class": "com.viz.ide.model.segment.SimpleTextSegmentData",
                "text": "Label"
            }
        },
        {
            "btnDone": {
                "@class": "com.viz.ide.model.segment.SimpleTextSegmentData",
                "text": "Done"
            },
            "lblAddRequest": {
                "@class": "com.viz.ide.model.segment.SimpleTextSegmentData",
                "text": "Label"
            },
            "lblAddRequestValue": {
                "@class": "com.viz.ide.model.segment.SimpleTextSegmentData",
                "text": "Label"
            },
            "lblAdded": {
                "@class": "com.viz.ide.model.segment.SimpleTextSegmentData",
                "text": "Label"
            },
            "lblAddedValue": {
                "@class": "com.viz.ide.model.segment.SimpleTextSegmentData",
                "text": "Label"
            },
            "lblAuctionId": {
                "@class": "com.viz.ide.model.segment.SimpleTextSegmentData",
                "text": "Label"
            },
            "lblAuctionIdValue": {
                "@class": "com.viz.ide.model.segment.SimpleTextSegmentData",
                "text": "Label"
            },
            "lblChassisNo": {
                "@class": "com.viz.ide.model.segment.SimpleTextSegmentData",
                "text": "Label"
            },
            "lblChassisNoValue": {
                "@class": "com.viz.ide.model.segment.SimpleTextSegmentData",
                "text": "Label"
            },
            "lblDone": {
                "@class": "com.viz.ide.model.segment.SimpleTextSegmentData",
                "text": "Label"
            },
            "lblLocation": {
                "@class": "com.viz.ide.model.segment.SimpleTextSegmentData",
                "text": "Label"
            },
            "lblLocationValue": {
                "@class": "com.viz.ide.model.segment.SimpleTextSegmentData",
                "text": "Label"
            },
            "lblModel": {
                "@class": "com.viz.ide.model.segment.SimpleTextSegmentData",
                "text": "Label"
            },
            "lblModelValue": {
                "@class": "com.viz.ide.model.segment.SimpleTextSegmentData",
                "text": "Label"
            },
            "lblTargetSellingPrice": {
                "@class": "com.viz.ide.model.segment.SimpleTextSegmentData",
                "text": "Label"
            },
            "lblUploadFile": {
                "@class": "com.viz.ide.model.segment.SimpleTextSegmentData",
                "text": "Label"
            },
            "lblUploadFileValue": {
                "@class": "com.viz.ide.model.segment.SimpleTextSegmentData",
                "text": "Label"
            },
            "lbltargetSellingPriceValue": {
                "@class": "com.viz.ide.model.segment.SimpleTextSegmentData",
                "text": "Label"
            }
        },
        {
            "btnDone": {
                "@class": "com.viz.ide.model.segment.SimpleTextSegmentData",
                "text": "Done"
            },
            "lblAddRequest": {
                "@class": "com.viz.ide.model.segment.SimpleTextSegmentData",
                "text": "Label"
            },
            "lblAddRequestValue": {
                "@class": "com.viz.ide.model.segment.SimpleTextSegmentData",
                "text": "Label"
            },
            "lblAdded": {
                "@class": "com.viz.ide.model.segment.SimpleTextSegmentData",
                "text": "Label"
            },
            "lblAddedValue": {
                "@class": "com.viz.ide.model.segment.SimpleTextSegmentData",
                "text": "Label"
            },
            "lblAuctionId": {
                "@class": "com.viz.ide.model.segment.SimpleTextSegmentData",
                "text": "Label"
            },
            "lblAuctionIdValue": {
                "@class": "com.viz.ide.model.segment.SimpleTextSegmentData",
                "text": "Label"
            },
            "lblChassisNo": {
                "@class": "com.viz.ide.model.segment.SimpleTextSegmentData",
                "text": "Label"
            },
            "lblChassisNoValue": {
                "@class": "com.viz.ide.model.segment.SimpleTextSegmentData",
                "text": "Label"
            },
            "lblDone": {
                "@class": "com.viz.ide.model.segment.SimpleTextSegmentData",
                "text": "Label"
            },
            "lblLocation": {
                "@class": "com.viz.ide.model.segment.SimpleTextSegmentData",
                "text": "Label"
            },
            "lblLocationValue": {
                "@class": "com.viz.ide.model.segment.SimpleTextSegmentData",
                "text": "Label"
            },
            "lblModel": {
                "@class": "com.viz.ide.model.segment.SimpleTextSegmentData",
                "text": "Label"
            },
            "lblModelValue": {
                "@class": "com.viz.ide.model.segment.SimpleTextSegmentData",
                "text": "Label"
            },
            "lblTargetSellingPrice": {
                "@class": "com.viz.ide.model.segment.SimpleTextSegmentData",
                "text": "Label"
            },
            "lblUploadFile": {
                "@class": "com.viz.ide.model.segment.SimpleTextSegmentData",
                "text": "Label"
            },
            "lblUploadFileValue": {
                "@class": "com.viz.ide.model.segment.SimpleTextSegmentData",
                "text": "Label"
            },
            "lbltargetSellingPriceValue": {
                "@class": "com.viz.ide.model.segment.SimpleTextSegmentData",
                "text": "Label"
            }
        },
        {
            "btnDone": {
                "@class": "com.viz.ide.model.segment.SimpleTextSegmentData",
                "text": "Done"
            },
            "lblAddRequest": {
                "@class": "com.viz.ide.model.segment.SimpleTextSegmentData",
                "text": "Label"
            },
            "lblAddRequestValue": {
                "@class": "com.viz.ide.model.segment.SimpleTextSegmentData",
                "text": "Label"
            },
            "lblAdded": {
                "@class": "com.viz.ide.model.segment.SimpleTextSegmentData",
                "text": "Label"
            },
            "lblAddedValue": {
                "@class": "com.viz.ide.model.segment.SimpleTextSegmentData",
                "text": "Label"
            },
            "lblAuctionId": {
                "@class": "com.viz.ide.model.segment.SimpleTextSegmentData",
                "text": "Label"
            },
            "lblAuctionIdValue": {
                "@class": "com.viz.ide.model.segment.SimpleTextSegmentData",
                "text": "Label"
            },
            "lblChassisNo": {
                "@class": "com.viz.ide.model.segment.SimpleTextSegmentData",
                "text": "Label"
            },
            "lblChassisNoValue": {
                "@class": "com.viz.ide.model.segment.SimpleTextSegmentData",
                "text": "Label"
            },
            "lblDone": {
                "@class": "com.viz.ide.model.segment.SimpleTextSegmentData",
                "text": "Label"
            },
            "lblLocation": {
                "@class": "com.viz.ide.model.segment.SimpleTextSegmentData",
                "text": "Label"
            },
            "lblLocationValue": {
                "@class": "com.viz.ide.model.segment.SimpleTextSegmentData",
                "text": "Label"
            },
            "lblModel": {
                "@class": "com.viz.ide.model.segment.SimpleTextSegmentData",
                "text": "Label"
            },
            "lblModelValue": {
                "@class": "com.viz.ide.model.segment.SimpleTextSegmentData",
                "text": "Label"
            },
            "lblTargetSellingPrice": {
                "@class": "com.viz.ide.model.segment.SimpleTextSegmentData",
                "text": "Label"
            },
            "lblUploadFile": {
                "@class": "com.viz.ide.model.segment.SimpleTextSegmentData",
                "text": "Label"
            },
            "lblUploadFileValue": {
                "@class": "com.viz.ide.model.segment.SimpleTextSegmentData",
                "text": "Label"
            },
            "lbltargetSellingPriceValue": {
                "@class": "com.viz.ide.model.segment.SimpleTextSegmentData",
                "text": "Label"
            }
        },
        {
            "btnDone": {
                "@class": "com.viz.ide.model.segment.SimpleTextSegmentData",
                "text": "Done"
            },
            "lblAddRequest": {
                "@class": "com.viz.ide.model.segment.SimpleTextSegmentData",
                "text": "Label"
            },
            "lblAddRequestValue": {
                "@class": "com.viz.ide.model.segment.SimpleTextSegmentData",
                "text": "Label"
            },
            "lblAdded": {
                "@class": "com.viz.ide.model.segment.SimpleTextSegmentData",
                "text": "Label"
            },
            "lblAddedValue": {
                "@class": "com.viz.ide.model.segment.SimpleTextSegmentData",
                "text": "Label"
            },
            "lblAuctionId": {
                "@class": "com.viz.ide.model.segment.SimpleTextSegmentData",
                "text": "Label"
            },
            "lblAuctionIdValue": {
                "@class": "com.viz.ide.model.segment.SimpleTextSegmentData",
                "text": "Label"
            },
            "lblChassisNo": {
                "@class": "com.viz.ide.model.segment.SimpleTextSegmentData",
                "text": "Label"
            },
            "lblChassisNoValue": {
                "@class": "com.viz.ide.model.segment.SimpleTextSegmentData",
                "text": "Label"
            },
            "lblDone": {
                "@class": "com.viz.ide.model.segment.SimpleTextSegmentData",
                "text": "Label"
            },
            "lblLocation": {
                "@class": "com.viz.ide.model.segment.SimpleTextSegmentData",
                "text": "Label"
            },
            "lblLocationValue": {
                "@class": "com.viz.ide.model.segment.SimpleTextSegmentData",
                "text": "Label"
            },
            "lblModel": {
                "@class": "com.viz.ide.model.segment.SimpleTextSegmentData",
                "text": "Label"
            },
            "lblModelValue": {
                "@class": "com.viz.ide.model.segment.SimpleTextSegmentData",
                "text": "Label"
            },
            "lblTargetSellingPrice": {
                "@class": "com.viz.ide.model.segment.SimpleTextSegmentData",
                "text": "Label"
            },
            "lblUploadFile": {
                "@class": "com.viz.ide.model.segment.SimpleTextSegmentData",
                "text": "Label"
            },
            "lblUploadFileValue": {
                "@class": "com.viz.ide.model.segment.SimpleTextSegmentData",
                "text": "Label"
            },
            "lbltargetSellingPriceValue": {
                "@class": "com.viz.ide.model.segment.SimpleTextSegmentData",
                "text": "Label"
            }
        },
        {
            "btnDone": {
                "@class": "com.viz.ide.model.segment.SimpleTextSegmentData",
                "text": "Done"
            },
            "lblAddRequest": {
                "@class": "com.viz.ide.model.segment.SimpleTextSegmentData",
                "text": "Label"
            },
            "lblAddRequestValue": {
                "@class": "com.viz.ide.model.segment.SimpleTextSegmentData",
                "text": "Label"
            },
            "lblAdded": {
                "@class": "com.viz.ide.model.segment.SimpleTextSegmentData",
                "text": "Label"
            },
            "lblAddedValue": {
                "@class": "com.viz.ide.model.segment.SimpleTextSegmentData",
                "text": "Label"
            },
            "lblAuctionId": {
                "@class": "com.viz.ide.model.segment.SimpleTextSegmentData",
                "text": "Label"
            },
            "lblAuctionIdValue": {
                "@class": "com.viz.ide.model.segment.SimpleTextSegmentData",
                "text": "Label"
            },
            "lblChassisNo": {
                "@class": "com.viz.ide.model.segment.SimpleTextSegmentData",
                "text": "Label"
            },
            "lblChassisNoValue": {
                "@class": "com.viz.ide.model.segment.SimpleTextSegmentData",
                "text": "Label"
            },
            "lblDone": {
                "@class": "com.viz.ide.model.segment.SimpleTextSegmentData",
                "text": "Label"
            },
            "lblLocation": {
                "@class": "com.viz.ide.model.segment.SimpleTextSegmentData",
                "text": "Label"
            },
            "lblLocationValue": {
                "@class": "com.viz.ide.model.segment.SimpleTextSegmentData",
                "text": "Label"
            },
            "lblModel": {
                "@class": "com.viz.ide.model.segment.SimpleTextSegmentData",
                "text": "Label"
            },
            "lblModelValue": {
                "@class": "com.viz.ide.model.segment.SimpleTextSegmentData",
                "text": "Label"
            },
            "lblTargetSellingPrice": {
                "@class": "com.viz.ide.model.segment.SimpleTextSegmentData",
                "text": "Label"
            },
            "lblUploadFile": {
                "@class": "com.viz.ide.model.segment.SimpleTextSegmentData",
                "text": "Label"
            },
            "lblUploadFileValue": {
                "@class": "com.viz.ide.model.segment.SimpleTextSegmentData",
                "text": "Label"
            },
            "lbltargetSellingPriceValue": {
                "@class": "com.viz.ide.model.segment.SimpleTextSegmentData",
                "text": "Label"
            }
        },
        {
            "btnDone": {
                "@class": "com.viz.ide.model.segment.SimpleTextSegmentData",
                "text": "Done"
            },
            "lblAddRequest": {
                "@class": "com.viz.ide.model.segment.SimpleTextSegmentData",
                "text": "Label"
            },
            "lblAddRequestValue": {
                "@class": "com.viz.ide.model.segment.SimpleTextSegmentData",
                "text": "Label"
            },
            "lblAdded": {
                "@class": "com.viz.ide.model.segment.SimpleTextSegmentData",
                "text": "Label"
            },
            "lblAddedValue": {
                "@class": "com.viz.ide.model.segment.SimpleTextSegmentData",
                "text": "Label"
            },
            "lblAuctionId": {
                "@class": "com.viz.ide.model.segment.SimpleTextSegmentData",
                "text": "Label"
            },
            "lblAuctionIdValue": {
                "@class": "com.viz.ide.model.segment.SimpleTextSegmentData",
                "text": "Label"
            },
            "lblChassisNo": {
                "@class": "com.viz.ide.model.segment.SimpleTextSegmentData",
                "text": "Label"
            },
            "lblChassisNoValue": {
                "@class": "com.viz.ide.model.segment.SimpleTextSegmentData",
                "text": "Label"
            },
            "lblDone": {
                "@class": "com.viz.ide.model.segment.SimpleTextSegmentData",
                "text": "Label"
            },
            "lblLocation": {
                "@class": "com.viz.ide.model.segment.SimpleTextSegmentData",
                "text": "Label"
            },
            "lblLocationValue": {
                "@class": "com.viz.ide.model.segment.SimpleTextSegmentData",
                "text": "Label"
            },
            "lblModel": {
                "@class": "com.viz.ide.model.segment.SimpleTextSegmentData",
                "text": "Label"
            },
            "lblModelValue": {
                "@class": "com.viz.ide.model.segment.SimpleTextSegmentData",
                "text": "Label"
            },
            "lblTargetSellingPrice": {
                "@class": "com.viz.ide.model.segment.SimpleTextSegmentData",
                "text": "Label"
            },
            "lblUploadFile": {
                "@class": "com.viz.ide.model.segment.SimpleTextSegmentData",
                "text": "Label"
            },
            "lblUploadFileValue": {
                "@class": "com.viz.ide.model.segment.SimpleTextSegmentData",
                "text": "Label"
            },
            "lbltargetSellingPriceValue": {
                "@class": "com.viz.ide.model.segment.SimpleTextSegmentData",
                "text": "Label"
            }
        },
        {
            "btnDone": {
                "@class": "com.viz.ide.model.segment.SimpleTextSegmentData",
                "text": "Done"
            },
            "lblAddRequest": {
                "@class": "com.viz.ide.model.segment.SimpleTextSegmentData",
                "text": "Label"
            },
            "lblAddRequestValue": {
                "@class": "com.viz.ide.model.segment.SimpleTextSegmentData",
                "text": "Label"
            },
            "lblAdded": {
                "@class": "com.viz.ide.model.segment.SimpleTextSegmentData",
                "text": "Label"
            },
            "lblAddedValue": {
                "@class": "com.viz.ide.model.segment.SimpleTextSegmentData",
                "text": "Label"
            },
            "lblAuctionId": {
                "@class": "com.viz.ide.model.segment.SimpleTextSegmentData",
                "text": "Label"
            },
            "lblAuctionIdValue": {
                "@class": "com.viz.ide.model.segment.SimpleTextSegmentData",
                "text": "Label"
            },
            "lblChassisNo": {
                "@class": "com.viz.ide.model.segment.SimpleTextSegmentData",
                "text": "Label"
            },
            "lblChassisNoValue": {
                "@class": "com.viz.ide.model.segment.SimpleTextSegmentData",
                "text": "Label"
            },
            "lblDone": {
                "@class": "com.viz.ide.model.segment.SimpleTextSegmentData",
                "text": "Label"
            },
            "lblLocation": {
                "@class": "com.viz.ide.model.segment.SimpleTextSegmentData",
                "text": "Label"
            },
            "lblLocationValue": {
                "@class": "com.viz.ide.model.segment.SimpleTextSegmentData",
                "text": "Label"
            },
            "lblModel": {
                "@class": "com.viz.ide.model.segment.SimpleTextSegmentData",
                "text": "Label"
            },
            "lblModelValue": {
                "@class": "com.viz.ide.model.segment.SimpleTextSegmentData",
                "text": "Label"
            },
            "lblTargetSellingPrice": {
                "@class": "com.viz.ide.model.segment.SimpleTextSegmentData",
                "text": "Label"
            },
            "lblUploadFile": {
                "@class": "com.viz.ide.model.segment.SimpleTextSegmentData",
                "text": "Label"
            },
            "lblUploadFileValue": {
                "@class": "com.viz.ide.model.segment.SimpleTextSegmentData",
                "text": "Label"
            },
            "lbltargetSellingPriceValue": {
                "@class": "com.viz.ide.model.segment.SimpleTextSegmentData",
                "text": "Label"
            }
        },
        {
            "btnDone": {
                "@class": "com.viz.ide.model.segment.SimpleTextSegmentData",
                "text": "Done"
            },
            "lblAddRequest": {
                "@class": "com.viz.ide.model.segment.SimpleTextSegmentData",
                "text": "Label"
            },
            "lblAddRequestValue": {
                "@class": "com.viz.ide.model.segment.SimpleTextSegmentData",
                "text": "Label"
            },
            "lblAdded": {
                "@class": "com.viz.ide.model.segment.SimpleTextSegmentData",
                "text": "Label"
            },
            "lblAddedValue": {
                "@class": "com.viz.ide.model.segment.SimpleTextSegmentData",
                "text": "Label"
            },
            "lblAuctionId": {
                "@class": "com.viz.ide.model.segment.SimpleTextSegmentData",
                "text": "Label"
            },
            "lblAuctionIdValue": {
                "@class": "com.viz.ide.model.segment.SimpleTextSegmentData",
                "text": "Label"
            },
            "lblChassisNo": {
                "@class": "com.viz.ide.model.segment.SimpleTextSegmentData",
                "text": "Label"
            },
            "lblChassisNoValue": {
                "@class": "com.viz.ide.model.segment.SimpleTextSegmentData",
                "text": "Label"
            },
            "lblDone": {
                "@class": "com.viz.ide.model.segment.SimpleTextSegmentData",
                "text": "Label"
            },
            "lblLocation": {
                "@class": "com.viz.ide.model.segment.SimpleTextSegmentData",
                "text": "Label"
            },
            "lblLocationValue": {
                "@class": "com.viz.ide.model.segment.SimpleTextSegmentData",
                "text": "Label"
            },
            "lblModel": {
                "@class": "com.viz.ide.model.segment.SimpleTextSegmentData",
                "text": "Label"
            },
            "lblModelValue": {
                "@class": "com.viz.ide.model.segment.SimpleTextSegmentData",
                "text": "Label"
            },
            "lblTargetSellingPrice": {
                "@class": "com.viz.ide.model.segment.SimpleTextSegmentData",
                "text": "Label"
            },
            "lblUploadFile": {
                "@class": "com.viz.ide.model.segment.SimpleTextSegmentData",
                "text": "Label"
            },
            "lblUploadFileValue": {
                "@class": "com.viz.ide.model.segment.SimpleTextSegmentData",
                "text": "Label"
            },
            "lbltargetSellingPriceValue": {
                "@class": "com.viz.ide.model.segment.SimpleTextSegmentData",
                "text": "Label"
            }
        },
        {
            "btnDone": {
                "@class": "com.viz.ide.model.segment.SimpleTextSegmentData",
                "text": "Done"
            },
            "lblAddRequest": {
                "@class": "com.viz.ide.model.segment.SimpleTextSegmentData",
                "text": "Label"
            },
            "lblAddRequestValue": {
                "@class": "com.viz.ide.model.segment.SimpleTextSegmentData",
                "text": "Label"
            },
            "lblAdded": {
                "@class": "com.viz.ide.model.segment.SimpleTextSegmentData",
                "text": "Label"
            },
            "lblAddedValue": {
                "@class": "com.viz.ide.model.segment.SimpleTextSegmentData",
                "text": "Label"
            },
            "lblAuctionId": {
                "@class": "com.viz.ide.model.segment.SimpleTextSegmentData",
                "text": "Label"
            },
            "lblAuctionIdValue": {
                "@class": "com.viz.ide.model.segment.SimpleTextSegmentData",
                "text": "Label"
            },
            "lblChassisNo": {
                "@class": "com.viz.ide.model.segment.SimpleTextSegmentData",
                "text": "Label"
            },
            "lblChassisNoValue": {
                "@class": "com.viz.ide.model.segment.SimpleTextSegmentData",
                "text": "Label"
            },
            "lblDone": {
                "@class": "com.viz.ide.model.segment.SimpleTextSegmentData",
                "text": "Label"
            },
            "lblLocation": {
                "@class": "com.viz.ide.model.segment.SimpleTextSegmentData",
                "text": "Label"
            },
            "lblLocationValue": {
                "@class": "com.viz.ide.model.segment.SimpleTextSegmentData",
                "text": "Label"
            },
            "lblModel": {
                "@class": "com.viz.ide.model.segment.SimpleTextSegmentData",
                "text": "Label"
            },
            "lblModelValue": {
                "@class": "com.viz.ide.model.segment.SimpleTextSegmentData",
                "text": "Label"
            },
            "lblTargetSellingPrice": {
                "@class": "com.viz.ide.model.segment.SimpleTextSegmentData",
                "text": "Label"
            },
            "lblUploadFile": {
                "@class": "com.viz.ide.model.segment.SimpleTextSegmentData",
                "text": "Label"
            },
            "lblUploadFileValue": {
                "@class": "com.viz.ide.model.segment.SimpleTextSegmentData",
                "text": "Label"
            },
            "lbltargetSellingPriceValue": {
                "@class": "com.viz.ide.model.segment.SimpleTextSegmentData",
                "text": "Label"
            }
        }
    ],
    "_height_": {
        "type": "string",
        "value": "100%"
    },
    "_indicator_": "none",
    "_left_": {
        "type": "string",
        "value": "0"
    },
    "_margin_": [
        0,
        0,
        0,
        0
    ],
    "_orientation_": 2,
    "_padding_": [
        0,
        0,
        0,
        0
    ],
    "_top_": {
        "type": "string",
        "value": "0"
    },
    "_width_": {
        "type": "string",
        "value": "100%"
    },
    "autogrowmode": 0,
    "canUpdateUI": true,
    "containerweight": 100,
    "counter": "09",
    "focusedindex": null,
    "focuseditem": null,
    "groupcells": false,
    "hasSections": false,
    "id": "segTableVehicle",
    "info": null,
    "ipad": {
        "psp": {
            "indicator": "rowselect"
        }
    },
    "iphone": {
        "psp": {
            "indicator": "rowselect"
        }
    },
    "iscustomlayout": false,
    "isvisible": true,
    "kuid": "ae24437dea7647bd82a9a9cbbdb8cb6b",
    "masterdata": {},
    "name": "kony.ui.SegmentedUI2",
    "needpageindicator": true,
    "pageoffdotimage": "pageoffdot.png",
    "pageondotimage": "pageondot.png",
    "paginationconfig": {
        "position": "bottom"
    },
    "parent": "flxTable",
    "pf": "frmMyVehicleNew",
    "retaincontentalignment": false,
    "retainflexpositionproperties": false,
    "retainselection": false,
    "rowTemplateId": "c9e4d21e0cfd484a8e5b097143dca22c",
    "rowcounter": 9,
    "rowfocusskin": "s961e586fe794e498e31c111fe40ef67",
    "rowskin": "s2d1a440627e4c3eb337995bf3931fdd",
    "rowtemplate": "flxSegVehicleTable",
    "screenlevelwidget": false,
    "seccounter": 0,
    "sectionheaderskin": "s394e25221a84c198a12829462d278f1",
    "selectedRows": null,
    "selectedState": false,
    "selectedindex": null,
    "selectedindices": null,
    "selecteditems": null,
    "selectedsectionindex": 0,
    "selectionbehavior": "default",
    "separatorcolor": "aaaaaa00",
    "separatorrequired": true,
    "separatorthickness": 1,
    "showscrollbars": false,
    "viewtype": "tableview",
    "vizProps": {},
    "wType": "Segment",
    "widgetalignment": 5,
    "widgetdatamap": {
        "btnDone": "btnDone",
        "flxSegVehicleTable": "flxSegVehicleTable",
        "flxVehicles": "flxVehicles",
        "lblAddRequest": "lblAddRequest",
        "lblAddRequestValue": "lblAddRequestValue",
        "lblAdded": "lblAdded",
        "lblAddedValue": "lblAddedValue",
        "lblAuctionId": "lblAuctionId",
        "lblAuctionIdValue": "lblAuctionIdValue",
        "lblChassisNo": "lblChassisNo",
        "lblChassisNoValue": "lblChassisNoValue",
        "lblDone": "lblDone",
        "lblLocation": "lblLocation",
        "lblLocationValue": "lblLocationValue",
        "lblModel": "lblModel",
        "lblModelValue": "lblModelValue",
        "lblTargetSellingPrice": "lblTargetSellingPrice",
        "lblUploadFile": "lblUploadFile",
        "lblUploadFileValue": "lblUploadFileValue",
        "lbltargetSellingPriceValue": "lbltargetSellingPriceValue"
    }
}