{
    "@class": "com.kony.gen.viz.model.component.KVizButton",
    "DNDConfig": null,
    "_height_": {
        "type": "string",
        "value": "50dp"
    },
    "_left_": {
        "type": "string",
        "value": "27dp"
    },
    "_margin_": [
        6,
        6,
        6,
        6
    ],
    "_padding_": [
        0,
        0,
        0,
        0
    ],
    "_skin_": "sced32e230a34deab454a433824a91d4",
    "_text_": "Go",
    "_top_": {
        "type": "string",
        "value": "90dp"
    },
    "_width_": {
        "type": "string",
        "value": "200dp"
    },
    "canUpdateUI": true,
    "centerx": {
        "type": "string",
        "value": "50%"
    },
    "containerweight": 100,
    "contentalignment": 5,
    "displaytext": true,
    "focusskin": "s3d87ba262864995afa373466fd12acb",
    "id": "btnIdentity",
    "ide_onClick": "AS_Button_b523337045464b59b16688cbed44c2f8",
    "info": null,
    "iscustomlayout": false,
    "isvisible": true,
    "kuid": "b39d90a8990b446fb5c332f0a2787d81",
    "name": "kony.ui.Button",
    "parent": "Identity",
    "pf": "Identity",
    "retaincontentalignment": false,
    "retainflexpositionproperties": false,
    "wType": "Button"
}